{
    "type": "FeatureCollection",
    "name": "mod",
    "crs": { "type": "name", "properties": { "name": "urn:ogc:def:crs:OGC:1.3:CRS84" } },
    "features": [
    { "type": "Feature", "properties": { "Name": "MOD"}, "geometry": { "type": "Point", "coordinates": [ -122.31248627323225, 47.65841609769019 ] } }
    ]
    }