{
    "type": "FeatureCollection",
    "name": "yifang",
    "crs": { "type": "name", "properties": { "name": "urn:ogc:def:crs:OGC:1.3:CRS84" } },
    "features": [
    { "type": "Feature", "properties": { "Name": "Yifang"}, "geometry": { "type": "Point", "coordinates": [ -122.31287528872464, 47.66534092062248 ] } }
    ]
    }